thlibs/__init__.py
thlibs/isphish.py
thlibs/sslchecker.py
thlibs/whois.py
threat_hunting_libs-0.0.5.dist-info/LICENSE
threat_hunting_libs-0.0.5.dist-info/METADATA
threat_hunting_libs-0.0.5.dist-info/WHEEL
threat_hunting_libs-0.0.5.dist-info/top_level.txt
threat_hunting_libs-0.0.5.dist-info/RECORD
