Metadata-Version: 2.2
Name: threat_hunting_libs
Version: 0.0.5
Summary: Libraries and modules to assist in threat hunting and research.
Home-page: https://github.com/h4cklife/threat_hunting
Author: h4cklife
Author-email: h4cklife_src@protonmail.com
Classifier: Programming Language :: Python :: 3
Classifier: License :: OSI Approved :: MIT License
Classifier: Operating System :: OS Independent
License-File: LICENSE
Requires-Dist: certifi
Requires-Dist: pytz
Dynamic: author
Dynamic: author-email
Dynamic: classifier
Dynamic: description
Dynamic: description-content-type
Dynamic: home-page
Dynamic: requires-dist
Dynamic: summary
